highwind/__init__.py
highwind/client.py
highwind/client_factory.py
highwind/deployment_inference.py
highwind/gradio_app.py
highwind/use_case.py
highwind-2.0.0.dist-info/LICENSE
highwind-2.0.0.dist-info/METADATA
highwind-2.0.0.dist-info/WHEEL
highwind-2.0.0.dist-info/RECORD
