Metadata-Version: 2.1
Name: highwind
Version: 2.0.0
Summary: Python SDK for Highwind (https://highwind.ai/)
Author: Melio AI, Inc.
Requires-Python: >=3.12.1,<4.0.0
Classifier: Programming Language :: Python :: 3
Requires-Dist: python-dotenv (>=1.0.1,<2.0.0)
Requires-Dist: requests (>=2.31.0,<3.0.0)
Requires-Dist: requests-mock (>=1.12.1,<2.0.0)
Requires-Dist: requests-oauthlib (>=2.0.0,<3.0.0)
